modelo_regressao/__init__.py
modelo_regressao/config.yml
modelo_regressao/pipeline.py
modelo_regressao/predicao.py
modelo_regressao/treino.py
modelo_regressao/config/__init__.py
modelo_regressao/config/core.py
modelo_regressao/datasets/__init__.py
modelo_regressao/modelos_treinados/__init__.py
modelo_regressao/modelos_treinados/modelo_output_v1.2.1.pkl
modelo_regressao/processamento/__init__.py
modelo_regressao/processamento/gerenciador_dados.py
modelo_regressao/processamento/validacao.py
Precos_Imoveis_SP-1.2.1.dist-info/LICENSE
Precos_Imoveis_SP-1.2.1.dist-info/METADATA
Precos_Imoveis_SP-1.2.1.dist-info/WHEEL
Precos_Imoveis_SP-1.2.1.dist-info/top_level.txt
Precos_Imoveis_SP-1.2.1.dist-info/RECORD
