Metadata-Version: 2.1
Name: Precos-Imoveis-SP
Version: 1.2.1
Summary: package contendo modelo de regressao para predicao de precos de imoveis
Home-page: https://github.com/GHM-ML
Author: GHM-ML
Author-email: gabe.hm.ml@gmail.com
License: MIT
Classifier: License :: OSI Approved :: MIT License
Classifier: Programming Language :: Python
Classifier: Programming Language :: Python :: 3
Classifier: Programming Language :: Python :: 3.6
Classifier: Programming Language :: Python :: 3.7
Classifier: Programming Language :: Python :: 3.8
Classifier: Programming Language :: Python :: 3.9
Classifier: Programming Language :: Python :: 3.10
Classifier: Programming Language :: Python :: Implementation :: CPython
Classifier: Programming Language :: Python :: Implementation :: PyPy
Requires-Python: >=3.6.0
License-File: LICENSE
Requires-Dist: google (==2.0.3)
Requires-Dist: google-api-python-client (==1.12.11)
Requires-Dist: openpyxl (==3.0.10)
Requires-Dist: numpy (>=1.21.0)
Requires-Dist: pandas (<1.4.0,>=1.3.5)
Requires-Dist: pydantic (<1.9.0,>=1.8.1)
Requires-Dist: scikit-learn (<1.1.0,>=1.0.2)
Requires-Dist: strictyaml (<1.4.0,>=1.3.2)
Requires-Dist: ruamel.yaml (==0.16.12)
Requires-Dist: feature-engine (<1.1.0,>=1.0.2)
Requires-Dist: joblib (<1.1.0,>=1.0.1)
